biobb_cp2k/__init__.py
biobb_cp2k/py.typed
biobb_cp2k/cp2k/__init__.py
biobb_cp2k/cp2k/common.py
biobb_cp2k/cp2k/cp2k_prep.py
biobb_cp2k/cp2k/cp2k_run.py
biobb_cp2k/cp2k/cp2k_data/ALL_BASIS_SETS
biobb_cp2k/cp2k/cp2k_data/ALL_POTENTIALS
biobb_cp2k/cp2k/cp2k_data/AcPP1_POTENTIALS
biobb_cp2k/cp2k/cp2k_data/BASIS_ADMM
biobb_cp2k/cp2k/cp2k_data/BASIS_ADMM_MOLOPT
biobb_cp2k/cp2k/cp2k_data/BASIS_ADMM_UZH
biobb_cp2k/cp2k/cp2k_data/BASIS_LRIGPW_AUXMOLOPT
biobb_cp2k/cp2k/cp2k_data/BASIS_MINIX
biobb_cp2k/cp2k/cp2k_data/BASIS_MOLOPT
biobb_cp2k/cp2k/cp2k_data/BASIS_MOLOPT_AcPP1
biobb_cp2k/cp2k/cp2k_data/BASIS_MOLOPT_LnPP1
biobb_cp2k/cp2k/cp2k_data/BASIS_MOLOPT_UCL
biobb_cp2k/cp2k/cp2k_data/BASIS_MOLOPT_UZH
biobb_cp2k/cp2k/cp2k_data/BASIS_RI_cc-TZ
biobb_cp2k/cp2k/cp2k_data/BASIS_SET
biobb_cp2k/cp2k/cp2k_data/BASIS_ZIJLSTRA
biobb_cp2k/cp2k/cp2k_data/BASIS_ccGRB_UZH
biobb_cp2k/cp2k/cp2k_data/BASIS_def2_QZVP_RI_ALL
biobb_cp2k/cp2k/cp2k_data/BASIS_pob
biobb_cp2k/cp2k/cp2k_data/ECP_POTENTIALS
biobb_cp2k/cp2k/cp2k_data/EMSL_BASIS_SETS
biobb_cp2k/cp2k/cp2k_data/GTH_BASIS_SETS
biobb_cp2k/cp2k/cp2k_data/GTH_POTENTIALS
biobb_cp2k/cp2k/cp2k_data/HFX_BASIS
biobb_cp2k/cp2k/cp2k_data/HF_POTENTIALS
biobb_cp2k/cp2k/cp2k_data/LnPP1_POTENTIALS
biobb_cp2k/cp2k/cp2k_data/MM_POTENTIAL
biobb_cp2k/cp2k/cp2k_data/NLCC_POTENTIALS
biobb_cp2k/cp2k/cp2k_data/POTENTIAL
biobb_cp2k/cp2k/cp2k_data/POTENTIAL_UZH
biobb_cp2k/cp2k/cp2k_data/README.md
biobb_cp2k/cp2k/cp2k_data/dftd3.dat
biobb_cp2k/cp2k/cp2k_data/nm12_parameters.xml
biobb_cp2k/cp2k/cp2k_data/rVV10_kernel_table.dat
biobb_cp2k/cp2k/cp2k_data/t_c_g.dat
biobb_cp2k/cp2k/cp2k_data/t_sh_p_s_c.dat
biobb_cp2k/cp2k/cp2k_data/vdW_kernel_table.dat
biobb_cp2k/cp2k/cp2k_data/xTB_parameters
biobb_cp2k/cp2k/cp2k_data/DFTB/uff_table
biobb_cp2k/cp2k/cp2k_data/DFTB/nonscc/bb
biobb_cp2k/cp2k/cp2k_data/DFTB/nonscc/bc
biobb_cp2k/cp2k/cp2k_data/DFTB/nonscc/bh
biobb_cp2k/cp2k/cp2k_data/DFTB/nonscc/bn
biobb_cp2k/cp2k/cp2k_data/DFTB/nonscc/cb
biobb_cp2k-5.2.0.dist-info/licenses/LICENSE
biobb_cp2k-5.2.0.dist-info/METADATA
biobb_cp2k-5.2.0.dist-info/WHEEL
biobb_cp2k-5.2.0.dist-info/entry_points.txt
biobb_cp2k-5.2.0.dist-info/top_level.txt
biobb_cp2k-5.2.0.dist-info/RECORD
